{
  "crq": [
    {
      "rfcAperti": "CRQ000000002332",
      "dataApertura": "2025-12-03",
      "anno": "2026.0",
      "emerg": "No",
      "utilizzato": "Sì",
      "categoria": "Open shift",
      "dataRilascio": "2026-01-04",
      "rifNostro": "Anto",
      "prj": "",
      "contenuto": "Switch Ateco 2025"
    },
    {
      "rfcAperti": "CRQ000000002450",
      "dataApertura": "2025-12-05",
      "anno": "2025.0",
      "emerg": "No",
      "utilizzato": "No",
      "categoria": "Open shift",
      "dataRilascio": "2025-12-17",
      "rifNostro": "Gess",
      "prj": "",
      "contenuto": "Proposte Anagrafiche: deploy post rilascio fallito in data 12/11 con RFC 12227352B.\neliminazione liquibase dal progetto.\nEventuale pulizia di lock dal db pre rilascio con script sql server"
    },
    {
      "rfcAperti": "CRQ000000003216",
      "dataApertura": "2025-12-09",
      "anno": "2026.0",
      "emerg": "No",
      "utilizzato": "Sì",
      "categoria": "Cobol",
      "dataRilascio": "2026-01-14",
      "rifNostro": "Marty",
      "prj": "",
      "contenuto": "AGBPCE11 - ateco 2007 a nuovo  + Puma giornaliero nuovo campo ateco"
    },
    {
      "rfcAperti": "CRQ000000003226",
      "dataApertura": "2025-12-17",
      "anno": "2026.0",
      "emerg": "No",
      "utilizzato": "Sì",
      "categoria": "Sched",
      "dataRilascio": "2026-01-07",
      "rifNostro": "Aini",
      "prj": "",
      "contenuto": "Correzione data deletion CHGJ021697"
    },
    {
      "rfcAperti": "CRQ000000002661",
      "dataApertura": "2025-12-11",
      "anno": "2026.0",
      "emerg": "No",
      "utilizzato": "Sì",
      "categoria": "Open shift",
      "dataRilascio": "2026-01-07",
      "rifNostro": "Richi",
      "prj": "bdesk",
      "contenuto": "redmine #109524 anagrafeGenerale/api/v2/collegamenti: sostituzione fallback da serviziwebprotetti a jdbc su DB2"
    },
    {
      "rfcAperti": "CRQ000000003165",
      "dataApertura": "2025-12-22",
      "anno": "2026.0",
      "emerg": "No",
      "utilizzato": "Sì",
      "categoria": "Open shift",
      "dataRilascio": "2026-01-14",
      "rifNostro": "Richi",
      "prj": "run",
      "contenuto": "ANNULLATO"
    },
    {
      "rfcAperti": "CRQ000000003226",
      "dataApertura": "2025-12-23",
      "anno": "2026.0",
      "emerg": "No",
      "utilizzato": "Sì",
      "categoria": "Sched",
      "dataRilascio": "2026-01-07",
      "rifNostro": "Nick",
      "prj": "",
      "contenuto": "Variazione JCL / PGM di data deletion"
    },
    {
      "rfcAperti": "CRQ000000002964",
      "dataApertura": "2025-12-17",
      "anno": "2026.0",
      "emerg": "No",
      "utilizzato": "Sì",
      "categoria": "Sched",
      "dataRilascio": "2026-01-09",
      "rifNostro": "Nick",
      "prj": "ddh",
      "contenuto": "Variazione Run Cycle per DDH da 2° sabato del trimestre a 3° sabato del trimestre"
    },
    {
      "rfcAperti": "CRQ000000003704",
      "dataApertura": "2026-01-08",
      "anno": "2026.0",
      "emerg": "No",
      "utilizzato": "Sì",
      "categoria": "Sched",
      "dataRilascio": "2026-01-14",
      "rifNostro": "Anto",
      "prj": "",
      "contenuto": "Switch flussi CRIF su piano YAG0C e YAG4A. Pacchetto changeman CHGJ021757"
    },
    {
      "rfcAperti": "CRQ000000004036",
      "dataApertura": "2026-01-14",
      "anno": "2026.0",
      "emerg": "No",
      "utilizzato": "Sì",
      "categoria": "Cobol",
      "dataRilascio": "2026-01-21",
      "rifNostro": "Giorgio + Nicola",
      "prj": "ring fence",
      "contenuto": "sistemazione programma AGBPBCSE per sistemazione errori nella fase YAG0553"
    },
    {
      "rfcAperti": "CRQ000000004088",
      "dataApertura": "2026-01-15",
      "anno": "2026.0",
      "emerg": "Sì",
      "utilizzato": "Sì",
      "categoria": "Sist",
      "dataRilascio": "2026-01-14",
      "rifNostro": "Anto",
      "prj": "",
      "contenuto": "Ripristino TRA1 CDC"
    },
    {
      "rfcAperti": "CRQ000000004355",
      "dataApertura": "2026-01-20",
      "anno": "2026.0",
      "emerg": "Sì",
      "utilizzato": "Sì",
      "categoria": "Cobol",
      "dataRilascio": "2026-01-20",
      "rifNostro": "Anto",
      "prj": "",
      "contenuto": "Rilascio urgente per fix agbpce11 per aggiornamento ateco pf titolari di"
    },
    {
      "rfcAperti": "CRQ000000004351",
      "dataApertura": "2026-01-20",
      "anno": "2026.0",
      "emerg": "No",
      "utilizzato": "Si",
      "categoria": "Open shift",
      "dataRilascio": "2026-01-28",
      "rifNostro": "Richi",
      "prj": "Poteri di Firma",
      "contenuto": "aggiornamento topic business \"core.anagrafe.cliente\": aggiunta di campi nullable (compatibility FULL) sugli eventi di business del topic core.anagrafe.cliente"
    },
    {
      "rfcAperti": "CRQ000000001826",
      "dataApertura": "2025-11-18",
      "anno": "2026.0",
      "emerg": "No",
      "utilizzato": "Sì",
      "categoria": "Sched",
      "dataRilascio": "2026-01-28",
      "rifNostro": "Nick",
      "prj": "",
      "contenuto": "Correzione jcl Postel XD9P"
    },
    {
      "rfcAperti": "CRQ000000004517",
      "dataApertura": "2026-01-22",
      "anno": "2026.0",
      "emerg": "No",
      "utilizzato": "Sì",
      "categoria": "Sched",
      "dataRilascio": "2026-02-04",
      "rifNostro": "Nick",
      "prj": "",
      "contenuto": "Variazione Run Cycle per DDH da 3° sabato del trimestre a 2° sabato del trimestre"
    },
    {
      "rfcAperti": "CRQ000000004616",
      "dataApertura": "2026-01-23",
      "anno": "2026.0",
      "emerg": "No",
      "utilizzato": "Sì",
      "categoria": "Open shift + DDL",
      "dataRilascio": "2026-02-04",
      "rifNostro": "Richi",
      "prj": "anagrafe",
      "contenuto": "particolarità anagrafiche: aggiunta operatore (con fix su loginquiry)"
    },
    {
      "rfcAperti": "CRQ000000004617",
      "dataApertura": "2026-01-23",
      "anno": "2026.0",
      "emerg": "No",
      "utilizzato": "Sì",
      "categoria": "Open shift",
      "dataRilascio": "2026-02-11",
      "rifNostro": "Richi",
      "prj": "anagrafe",
      "contenuto": "contatti certificati aziendali"
    },
    {
      "rfcAperti": "CRQ000000004581",
      "dataApertura": "2026-01-26",
      "anno": "2026.0",
      "emerg": "No",
      "utilizzato": "Sì",
      "categoria": "Open shift",
      "dataRilascio": "2026-02-11",
      "rifNostro": "Richi",
      "prj": "concert",
      "contenuto": "contatti certificati aziendali"
    },
    {
      "rfcAperti": "CRQ000000001860",
      "dataApertura": "2025-11-19",
      "anno": "2025",
      "emerg": "No",
      "utilizzato": "Si",
      "categoria": "Schedulazione (TWS/JCL)",
      "dataRilascio": "2025-12-05",
      "rifNostro": "Fra",
      "prj": "Poteri Di Firma",
      "contenuto": "Creazione YPF01, YPF0C e YPF1C"
    },
    {
      "rfcAperti": "CRQ000000001800",
      "dataApertura": "2025-11-19",
      "anno": "2025",
      "emerg": "No",
      "utilizzato": "Si",
      "categoria": "Openshift",
      "dataRilascio": "2025-12-03",
      "rifNostro": "Fra",
      "prj": "Poteri di Firma",
      "contenuto": "Primo rilascio applicativo silente Poteri Di Firma. Esecuzione DDL Oracle per impianto DB"
    },
    {
      "rfcAperti": "CRQ000000001901",
      "dataApertura": "2025-11-19",
      "anno": "2025",
      "emerg": "No",
      "utilizzato": "Si",
      "categoria": "Openshift",
      "dataRilascio": "2025-12-05",
      "rifNostro": "Fra",
      "prj": "Poteri di Firma",
      "contenuto": "Rilascio layer batch + fix"
    },
    {
      "rfcAperti": "CRQ000000001862",
      "dataApertura": "2025-12-19",
      "anno": "2025",
      "emerg": "No",
      "utilizzato": "No",
      "categoria": "Openshift",
      "dataRilascio": "2025-12-10",
      "rifNostro": "Fra",
      "prj": "Poteri Di Firma",
      "contenuto": "ANNULLATO"
    },
    {
      "rfcAperti": "CRQ000000001864",
      "dataApertura": "2025-12-19",
      "anno": "2025",
      "emerg": "No",
      "utilizzato": "No",
      "categoria": "Openshift",
      "dataRilascio": "2025-12-17",
      "rifNostro": "Fra",
      "prj": "Poteri di Firma",
      "contenuto": "ANNULLATO"
    },
    {
      "rfcAperti": "CRQ000000001865",
      "dataApertura": "2025-12-19",
      "anno": "2025",
      "emerg": "No",
      "utilizzato": "Si",
      "categoria": "Openshift",
      "dataRilascio": "2025-12-17",
      "rifNostro": "Fra",
      "prj": "Poteri di Firma",
      "contenuto": "GOLIVE - fix post rilasci precedenti"
    },
    {
      "rfcAperti": "CRQ000000002557",
      "dataApertura": "2025-12-10",
      "anno": "2026",
      "emerg": "No",
      "utilizzato": "Si",
      "categoria": "Schedulazione (TWS/JCL)",
      "dataRilascio": "2026-01-07",
      "rifNostro": "Fra",
      "prj": "Poteri di Firma",
      "contenuto": "Modifica piani batch per problema invocazione layer bh openshift"
    },
    {
      "rfcAperti": "CRQ000000003054",
      "dataApertura": "2025-12-18",
      "anno": "2026",
      "emerg": "No",
      "utilizzato": "Si",
      "categoria": "Openshift",
      "dataRilascio": "2026-01-09",
      "rifNostro": "Fra",
      "prj": "Poteri di Firma",
      "contenuto": "fix stringa mount"
    },
    {
      "rfcAperti": "CRQ000000003788",
      "dataApertura": "2026-01-09",
      "anno": "2026",
      "emerg": "No",
      "utilizzato": "Si",
      "categoria": "Openshift",
      "dataRilascio": "2026-01-16",
      "rifNostro": "Fra",
      "prj": "Poteri di Firma",
      "contenuto": "Rilascio fix segnalazioni fase pilota"
    },
    {
      "rfcAperti": "CRQ000000003964",
      "dataApertura": "2026-01-13",
      "anno": "2026",
      "emerg": "No",
      "utilizzato": "Si",
      "categoria": "Openshift",
      "dataRilascio": "2026-01-28",
      "rifNostro": "Fra",
      "prj": "Poteri di Firma",
      "contenuto": "Fix redmine fase pilota"
    },
    {
      "rfcAperti": "CRQ000000004271",
      "dataApertura": "2026-01-20",
      "anno": "2026",
      "emerg": "No",
      "utilizzato": "No",
      "categoria": "Openshift",
      "dataRilascio": "2026-02-04",
      "rifNostro": "Fra",
      "prj": "Poteri di Firma",
      "contenuto": "fix redmine pilota"
    },
    {
      "rfcAperti": "CRQ000000004664",
      "dataApertura": "2026-02-27",
      "anno": "2026",
      "emerg": "No",
      "utilizzato": "No",
      "categoria": "Schedulazione (TWS/JCL)",
      "dataRilascio": "2026-02-04",
      "rifNostro": "Fra",
      "prj": "Poteri di Firma",
      "contenuto": "Scambio flussi con CRIF"
    }
  ]
}